drymass/__init__.py
drymass/_version.py
drymass/_version_save.py
drymass/anasphere.py
drymass/converter.py
drymass/extractroi.py
drymass/roi.py
drymass/search.py
drymass/threshold.py
drymass/util.py
drymass/cli/__init__.py
drymass/cli/analyzing.py
drymass/cli/config.py
drymass/cli/converting.py
drymass/cli/definitions.py
drymass/cli/dialog.py
drymass/cli/extracting.py
drymass/cli/parse_funcs.py
drymass/cli/plot.py
drymass/cli/profile.py
drymass/cli/task_watcher.py
drymass-0.12.0.dist-info/LICENSE
drymass-0.12.0.dist-info/METADATA
drymass-0.12.0.dist-info/WHEEL
drymass-0.12.0.dist-info/entry_points.txt
drymass-0.12.0.dist-info/top_level.txt
drymass-0.12.0.dist-info/RECORD
