Metadata-Version: 2.1
Name: drymass
Version: 0.12.0
Summary: manipulation and analysis of phase microscopy data
Home-page: https://github.com/RI-imaging/DryMass
Author: Paul Müller
Author-email: dev@craban.de
License: MIT
Keywords: digital holographic microscopy,optics,quantitative phase imaging,refractive index,scattering
Platform: ALL
Classifier: Operating System :: OS Independent
Classifier: Programming Language :: Python :: 3
Classifier: Intended Audience :: Science/Research
Requires-Python: >=3.9, <4
License-File: LICENSE
Requires-Dist: appdirs
Requires-Dist: matplotlib (>=2.2.0)
Requires-Dist: numpy (>=1.12.0)
Requires-Dist: qpformat (>=0.14.0)
Requires-Dist: qpimage (>=0.9.1)
Requires-Dist: qpretrieve (>=0.2.8)
Requires-Dist: qpsphere (>=0.5.9)
Requires-Dist: scikit-image (>=0.16.1)
Requires-Dist: tifffile (==2020.5.25)
